data_migration/__init__.py
data_migration/apps.py
data_migration/helper.py
data_migration/settings.py
data_migration/management/__init__.py
data_migration/management/commands/__init__.py
data_migration/management/commands/data_migrate.py
data_migration/management/commands/django_makemigrations.py
data_migration/management/commands/django_migrate.py
data_migration/management/commands/django_squashmigrations.py
data_migration/management/commands/makemigrations.py
data_migration/management/commands/migrate.py
data_migration/management/commands/squashmigrations.py
data_migration/services/__init__.py
data_migration/services/file_generator.py
data_migration/services/graph.py
data_migration/services/node.py
data_migration/services/squasher.py
data_migration/services/templates/migration.py.txt
django_data_migrations-0.1.5.dist-info/LICENSE
django_data_migrations-0.1.5.dist-info/METADATA
django_data_migrations-0.1.5.dist-info/WHEEL
django_data_migrations-0.1.5.dist-info/top_level.txt
django_data_migrations-0.1.5.dist-info/RECORD
