Metadata-Version: 2.1
Name: django-data-migrations
Version: 0.1.5
Summary: Extraction tool for data only django migrations
Home-page: https://github.com/philsupertramp/django-data-migration/
Author: Philipp Zettl
Author-email: philipp.zett@godesteem.de
License: MIT
Keywords: django,database migrations
Classifier: Development Status :: 4 - Beta
Classifier: Environment :: Web Environment
Classifier: Framework :: Django
Classifier: Framework :: Django :: 3.0
Classifier: Framework :: Django :: 3.1
Classifier: Framework :: Django :: 3.2
Classifier: Framework :: Django :: 2.2
Classifier: Intended Audience :: Developers
Classifier: License :: OSI Approved :: MIT License
Classifier: Operating System :: OS Independent
Classifier: Programming Language :: Python
Classifier: Programming Language :: Python :: 3
Classifier: Programming Language :: Python :: 3 :: Only
Classifier: Programming Language :: Python :: 3.6
Classifier: Programming Language :: Python :: 3.7
Classifier: Programming Language :: Python :: 3.8
Classifier: Topic :: Internet :: WWW/HTTP
Classifier: Topic :: Internet :: WWW/HTTP :: Dynamic Content
License-File: LICENSE
Requires-Dist: django (>=2.2)
